MANIFEST.in
setup.py
contendo_finance_insights/README.md
contendo_finance_insights/SimpleStatsGenerator.py
contendo_finance_insights/__init__.py
contendo_finance_insights/contendo_finance_config.py
contendo_finance_insights/finance_service_manager.py
contendo_finance_insights/finance_stats_generator.py
contendo_finance_insights/get_stock_news.py
contendo_finance_insights/get_stocks_data.py
contendo_finance_insights/google_trend_import.py
contendo_finance_insights/stock_metrics_calculator.py
contendo_finance_insights.egg-info/PKG-INFO
contendo_finance_insights.egg-info/SOURCES.txt
contendo_finance_insights.egg-info/dependency_links.txt
contendo_finance_insights.egg-info/not-zip-safe
contendo_finance_insights.egg-info/requires.txt
contendo_finance_insights.egg-info/top_level.txt
contendo_finance_insights/queries/top_lists_query.sql