Metadata-Version: 1.0
Name: contendo-finance-insights
Version: 0.1.26
Summary: contendo.ai finance insights package
Home-page: https://github.com/Yahalis/contendo_finance/tree/master/finance_insights
Author: Yahali Sherman, contendo.ai
Author-email: yahali@contendo.ai
License: APACHE2
Platform: UNKNOWN
